aibs_informatics_aws_lambda/__init__.py
aibs_informatics_aws_lambda/_version.py
aibs_informatics_aws_lambda/main.py
aibs_informatics_aws_lambda/py.typed
aibs_informatics_aws_lambda/common/__init__.py
aibs_informatics_aws_lambda/common/base.py
aibs_informatics_aws_lambda/common/handler.py
aibs_informatics_aws_lambda/common/logging.py
aibs_informatics_aws_lambda/common/metrics.py
aibs_informatics_aws_lambda/common/models.py
aibs_informatics_aws_lambda/common/api/__init__.py
aibs_informatics_aws_lambda/common/api/handler.py
aibs_informatics_aws_lambda/common/api/resolver.py
aibs_informatics_aws_lambda/handlers/__init__.py
aibs_informatics_aws_lambda/handlers/batch/__init__.py
aibs_informatics_aws_lambda/handlers/batch/create.py
aibs_informatics_aws_lambda/handlers/batch/model.py
aibs_informatics_aws_lambda/handlers/data_sync/__init__.py
aibs_informatics_aws_lambda/handlers/data_sync/file_system.py
aibs_informatics_aws_lambda/handlers/data_sync/model.py
aibs_informatics_aws_lambda/handlers/data_sync/operations.py
aibs_informatics_aws_lambda/handlers/demand/__init__.py
aibs_informatics_aws_lambda/handlers/demand/context_manager.py
aibs_informatics_aws_lambda/handlers/demand/model.py
aibs_informatics_aws_lambda/handlers/demand/scaffolding.py
aibs_informatics_aws_lambda/handlers/ecr/__init__.py
aibs_informatics_aws_lambda/handlers/ecr/replicate_image.py
aibs_informatics_aws_lambda/handlers/notifications/__init__.py
aibs_informatics_aws_lambda/handlers/notifications/model.py
aibs_informatics_aws_lambda/handlers/notifications/router.py
aibs_informatics_aws_lambda/handlers/notifications/notifiers/__init__.py
aibs_informatics_aws_lambda/handlers/notifications/notifiers/base.py
aibs_informatics_aws_lambda/handlers/notifications/notifiers/model.py
aibs_informatics_aws_lambda/handlers/notifications/notifiers/ses.py
aibs_informatics_aws_lambda/handlers/notifications/notifiers/sns.py
aibs_informatics_aws_lambda-0.0.12.dist-info/licenses/LICENSE
aibs_informatics_aws_lambda-0.0.12.dist-info/METADATA
aibs_informatics_aws_lambda-0.0.12.dist-info/WHEEL
aibs_informatics_aws_lambda-0.0.12.dist-info/entry_points.txt
aibs_informatics_aws_lambda-0.0.12.dist-info/top_level.txt
aibs_informatics_aws_lambda-0.0.12.dist-info/RECORD
