Metadata-Version: 2.4
Name: aibs-informatics-aws-lambda
Version: 0.0.12
Summary: Utility library for building validated and typed AWS Lambda functions
Author-email: AIBS Informatics Group <marmot@alleninstitute.onmicrosoft.com>
Maintainer-email: AIBS Informatics Group <marmot@alleninstitute.onmicrosoft.com>
Project-URL: Documentation, https://.github.io/aibs-informatics-aws-lambda/
Project-URL: Homepage, https://github.com/AllenInstitute/aibs-informatics-aws-lambda/
Project-URL: Issues, https://github.com/AllenInstitute/aibs-informatics-aws-lambda/issues
Project-URL: Repository, https://github.com/AllenInstitute/aibs-informatics-aws-lambda/
Requires-Python: >=3.9
License-File: LICENSE
Requires-Dist: aibs-informatics-aws-utils<1,>=0.0.8
Requires-Dist: aibs-informatics-core<1,>=0.2.4
Requires-Dist: aws-lambda-powertools~=2.35
Requires-Dist: pydantic<3,>=2.0.3
Requires-Dist: aws-lambda-typing
Dynamic: license-file
